pyvenice/__init__.py
pyvenice/api_keys.py
pyvenice/audio.py
pyvenice/billing.py
pyvenice/characters.py
pyvenice/chat.py
pyvenice/client.py
pyvenice/deprecation.py
pyvenice/embeddings.py
pyvenice/exceptions.py
pyvenice/image.py
pyvenice/models.py
pyvenice/py.typed
pyvenice/validators.py
pyvenice-0.3.1.dist-info/licenses/LICENSE
pyvenice-0.3.1.dist-info/METADATA
pyvenice-0.3.1.dist-info/WHEEL
pyvenice-0.3.1.dist-info/top_level.txt
pyvenice-0.3.1.dist-info/RECORD
