Metadata-Version: 2.4
Name: pyvenice
Version: 0.3.1
Summary: A comprehensive Python client for the Venice.ai API with automatic parameter validation
Author-email: Kieran Bicheno <kieran@bicheno.me>
Maintainer-email: Kieran Bicheno <kieran@bicheno.me>
License-Expression: MIT
Project-URL: Homepage, https://github.com/TheLustriVA/PyVenice
Project-URL: Bug Tracker, https://github.com/TheLustriVA/PyVenice/issues
Project-URL: Documentation, https://github.com/TheLustriVA/PyVenice#readme
Project-URL: Source Code, https://github.com/TheLustriVA/PyVenice
Keywords: venice,ai,api,client,llm,chatgpt,gpt,claude,anthropic
Classifier: Development Status :: 4 - Beta
Classifier: Intended Audience :: Developers
Classifier: Programming Language :: Python :: 3
Classifier: Programming Language :: Python :: 3.12
Classifier: Programming Language :: Python :: 3.13
Classifier: Topic :: Software Development :: Libraries :: Python Modules
Classifier: Topic :: Internet :: WWW/HTTP
Classifier: Topic :: Scientific/Engineering :: Artificial Intelligence
Requires-Python: >=3.12
License-File: LICENSE
Requires-Dist: httpx>=0.27.0
Requires-Dist: pydantic>=2.0.0
Requires-Dist: python-dateutil>=2.8.0
Requires-Dist: typing-extensions>=4.0.0
Provides-Extra: test
Requires-Dist: pytest>=7.0.0; extra == "test"
Requires-Dist: pytest-cov>=4.0.0; extra == "test"
Requires-Dist: pytest-asyncio>=0.21.0; extra == "test"
Requires-Dist: respx>=0.20.0; extra == "test"
Requires-Dist: freezegun>=1.2.0; extra == "test"
Provides-Extra: dev
Requires-Dist: pyvenice[test]; extra == "dev"
Requires-Dist: black>=23.0.0; extra == "dev"
Requires-Dist: ruff>=0.1.0; extra == "dev"
Requires-Dist: build>=1.0.0; extra == "dev"
Requires-Dist: twine>=4.0.0; extra == "dev"
Dynamic: license-file
